Metadata-Version: 1.1
Name: dtool-overlay
Version: 0.3.1
Summary: dtool CLI utilities for working with per item metadata
Home-page: https://github.com/jic-dtool/dtool-overlay
Author: Tjelvar Olsson
Author-email: tjelvar.olsson@gmail.com
License: MIT
Download-URL: https://github.com/jic-dtool/dtool-overlay/tarball/0.3.1
Platform: UNKNOWN
